streamlit_custom_api_grid/JsCode.py
streamlit_custom_api_grid/__init__.py
streamlit_custom_api_grid/constant.py
streamlit_custom_api_grid/grid_options_builder.py
streamlit_custom_api_grid/test_app.py
streamlit_custom_api_grid/frontend/build/asset-manifest.json
streamlit_custom_api_grid/frontend/build/bootstrap.min.css
streamlit_custom_api_grid/frontend/build/bootstrap.min.css.map
streamlit_custom_api_grid/frontend/build/index.html
streamlit_custom_api_grid/frontend/build/precache-manifest.ff41946658ac18947188c831b040219c.js
streamlit_custom_api_grid/frontend/build/service-worker.js
streamlit_custom_api_grid/frontend/build/static/css/2.739f1b7f.chunk.css
streamlit_custom_api_grid/frontend/build/static/css/2.739f1b7f.chunk.css.map
streamlit_custom_api_grid/frontend/build/static/css/main.e65f1e72.chunk.css
streamlit_custom_api_grid/frontend/build/static/css/main.e65f1e72.chunk.css.map
streamlit_custom_api_grid/frontend/build/static/js/2.4e6653df.chunk.js
streamlit_custom_api_grid/frontend/build/static/js/2.4e6653df.chunk.js.LICENSE.txt
streamlit_custom_api_grid/frontend/build/static/js/2.4e6653df.chunk.js.map
streamlit_custom_api_grid/frontend/build/static/js/main.6d593e2b.chunk.js
streamlit_custom_api_grid/frontend/build/static/js/main.6d593e2b.chunk.js.map
streamlit_custom_api_grid/frontend/build/static/js/runtime-main.1f7e4d05.js
streamlit_custom_api_grid/frontend/build/static/js/runtime-main.1f7e4d05.js.map
streamlit_custom_api_grid/frontend/public/bootstrap.min.css
streamlit_custom_api_grid/frontend/public/bootstrap.min.css.map
streamlit_custom_api_grid/frontend/public/index.html
streamlit_custom_api_grid/frontend/src/Aggrid.tsx
streamlit_custom_api_grid/frontend/src/Main.tsx
streamlit_custom_api_grid/frontend/src/index.tsx
streamlit_custom_api_grid/frontend/src/interfaces.ts
streamlit_custom_api_grid/frontend/src/react-app-env.d.ts
streamlit_custom_api_grid/frontend/src/styles.css
streamlit_custom_api_grid/frontend/src/utils.js
streamlit_custom_api_grid-0.1.4.dist-info/licenses/LICENSE
streamlit_custom_api_grid-0.1.4.dist-info/METADATA
streamlit_custom_api_grid-0.1.4.dist-info/WHEEL
streamlit_custom_api_grid-0.1.4.dist-info/top_level.txt
streamlit_custom_api_grid-0.1.4.dist-info/RECORD
