Metadata-Version: 2.4
Name: streamlit-custom_api_grid
Version: 0.1.4
Summary: A Streamlit Aggrid custom component with Custom Button Modal and API integration
Home-page: https://github.com/nafets33/streamlit_custom_api_grid
Author: Stefan Stapinski
Author-email: stefanstapinski@gmail.com
Project-URL: Bug Tracker, https://github.com/nafets33/streamlit_custom_api_grid/issues
Requires-Python: >=3.7
License-File: LICENSE
Requires-Dist: streamlit>=1.0.0
Dynamic: author
Dynamic: author-email
Dynamic: description
Dynamic: description-content-type
Dynamic: home-page
Dynamic: license-file
Dynamic: project-url
Dynamic: requires-dist
Dynamic: requires-python
Dynamic: summary
